{
	"textures": [
		{
			"image": "atlas.png",
			"format": "RGBA8888",
			"size": {
				"w": 317,
				"h": 127
			},
			"scale": 1,
			"frames": [
				{
					"filename": "atrium/atrium.png",
					"rotated": false,
					"trimmed": false,
					"sourceSize": {
						"w": 200,
						"h": 100
					},
					"spriteSourceSize": {
						"x": 0,
						"y": 0,
						"w": 200,
						"h": 100
					},
					"frame": {
						"x": 1,
						"y": 1,
						"w": 200,
						"h": 100
					}
				},
				{
					"filename": "atrium/table-and-chairs.png",
					"rotated": false,
					"trimmed": true,
					"sourceSize": {
						"w": 60,
						"h": 30
					},
					"spriteSourceSize": {
						"x": 2,
						"y": 5,
						"w": 56,
						"h": 23
					},
					"frame": {
						"x": 1,
						"y": 103,
						"w": 56,
						"h": 23
					}
				},
				{
					"filename": "walkcycle/walkcycle-02.png",
					"rotated": false,
					"trimmed": true,
					"sourceSize": {
						"w": 14,
						"h": 35
					},
					"spriteSourceSize": {
						"x": 1,
						"y": 1,
						"w": 13,
						"h": 34
					},
					"frame": {
						"x": 203,
						"y": 1,
						"w": 13,
						"h": 34
					}
				},
				{
					"filename": "walkcycle/walkcycle-01.png",
					"rotated": false,
					"trimmed": true,
					"sourceSize": {
						"w": 14,
						"h": 35
					},
					"spriteSourceSize": {
						"x": 2,
						"y": 1,
						"w": 12,
						"h": 34
					},
					"frame": {
						"x": 203,
						"y": 37,
						"w": 12,
						"h": 34
					}
				},
				{
					"filename": "walkcycle/walkcycle-05.png",
					"rotated": false,
					"trimmed": true,
					"sourceSize": {
						"w": 14,
						"h": 35
					},
					"spriteSourceSize": {
						"x": 2,
						"y": 1,
						"w": 12,
						"h": 34
					},
					"frame": {
						"x": 203,
						"y": 73,
						"w": 12,
						"h": 34
					}
				},
				{
					"filename": "walkcycle/walkcycle-06.png",
					"rotated": false,
					"trimmed": true,
					"sourceSize": {
						"w": 14,
						"h": 35
					},
					"spriteSourceSize": {
						"x": 1,
						"y": 1,
						"w": 12,
						"h": 34
					},
					"frame": {
						"x": 217,
						"y": 37,
						"w": 12,
						"h": 34
					}
				},
				{
					"filename": "walkcycle/walkcycle-03.png",
					"rotated": false,
					"trimmed": true,
					"sourceSize": {
						"w": 14,
						"h": 35
					},
					"spriteSourceSize": {
						"x": 0,
						"y": 2,
						"w": 14,
						"h": 33
					},
					"frame": {
						"x": 218,
						"y": 1,
						"w": 14,
						"h": 33
					}
				},
				{
					"filename": "walkcycle/walkcycle-07.png",
					"rotated": false,
					"trimmed": true,
					"sourceSize": {
						"w": 14,
						"h": 35
					},
					"spriteSourceSize": {
						"x": 0,
						"y": 2,
						"w": 14,
						"h": 33
					},
					"frame": {
						"x": 217,
						"y": 73,
						"w": 14,
						"h": 33
					}
				},
				{
					"filename": "walkcycle/walkcycle-04.png",
					"rotated": false,
					"trimmed": true,
					"sourceSize": {
						"w": 14,
						"h": 35
					},
					"spriteSourceSize": {
						"x": 1,
						"y": 2,
						"w": 13,
						"h": 33
					},
					"frame": {
						"x": 231,
						"y": 36,
						"w": 13,
						"h": 33
					}
				},
				{
					"filename": "walkcycle/walkcycle-08.png",
					"rotated": false,
					"trimmed": true,
					"sourceSize": {
						"w": 14,
						"h": 35
					},
					"spriteSourceSize": {
						"x": 1,
						"y": 2,
						"w": 12,
						"h": 33
					},
					"frame": {
						"x": 234,
						"y": 1,
						"w": 12,
						"h": 33
					}
				},
				{
					"filename": "walkcycle/walkcycle-09.png",
					"rotated": false,
					"trimmed": true,
					"sourceSize": {
						"w": 14,
						"h": 35
					},
					"spriteSourceSize": {
						"x": 1,
						"y": 2,
						"w": 12,
						"h": 33
					},
					"frame": {
						"x": 233,
						"y": 71,
						"w": 12,
						"h": 33
					}
				},
				{
					"filename": "walkcycle/walkcycle-10.png",
					"rotated": false,
					"trimmed": true,
					"sourceSize": {
						"w": 14,
						"h": 35
					},
					"spriteSourceSize": {
						"x": 1,
						"y": 2,
						"w": 12,
						"h": 33
					},
					"frame": {
						"x": 246,
						"y": 36,
						"w": 12,
						"h": 33
					}
				},
				{
					"filename": "walkcycle/walkcycle-11.png",
					"rotated": false,
					"trimmed": true,
					"sourceSize": {
						"w": 14,
						"h": 35
					},
					"spriteSourceSize": {
						"x": 1,
						"y": 2,
						"w": 12,
						"h": 33
					},
					"frame": {
						"x": 248,
						"y": 1,
						"w": 12,
						"h": 33
					}
				},
				{
					"filename": "walkcycle/walkcycle-12.png",
					"rotated": false,
					"trimmed": true,
					"sourceSize": {
						"w": 14,
						"h": 35
					},
					"spriteSourceSize": {
						"x": 1,
						"y": 2,
						"w": 12,
						"h": 33
					},
					"frame": {
						"x": 247,
						"y": 71,
						"w": 12,
						"h": 33
					}
				},
				{
					"filename": "walkcycle/walkcycle-13.png",
					"rotated": false,
					"trimmed": true,
					"sourceSize": {
						"w": 14,
						"h": 35
					},
					"spriteSourceSize": {
						"x": 1,
						"y": 2,
						"w": 12,
						"h": 33
					},
					"frame": {
						"x": 260,
						"y": 36,
						"w": 12,
						"h": 33
					}
				},
				{
					"filename": "walkcycle/walkcycle-14.png",
					"rotated": false,
					"trimmed": true,
					"sourceSize": {
						"w": 14,
						"h": 35
					},
					"spriteSourceSize": {
						"x": 1,
						"y": 2,
						"w": 12,
						"h": 33
					},
					"frame": {
						"x": 262,
						"y": 1,
						"w": 12,
						"h": 33
					}
				},
				{
					"filename": "walkcycle/walkcycle-15.png",
					"rotated": false,
					"trimmed": true,
					"sourceSize": {
						"w": 14,
						"h": 35
					},
					"spriteSourceSize": {
						"x": 1,
						"y": 2,
						"w": 12,
						"h": 33
					},
					"frame": {
						"x": 261,
						"y": 71,
						"w": 12,
						"h": 33
					}
				},
				{
					"filename": "walkcycle/walkcycle-16.png",
					"rotated": false,
					"trimmed": true,
					"sourceSize": {
						"w": 14,
						"h": 35
					},
					"spriteSourceSize": {
						"x": 1,
						"y": 2,
						"w": 12,
						"h": 33
					},
					"frame": {
						"x": 274,
						"y": 36,
						"w": 12,
						"h": 33
					}
				},
				{
					"filename": "walkcycle/walkcycle-17.png",
					"rotated": false,
					"trimmed": true,
					"sourceSize": {
						"w": 14,
						"h": 35
					},
					"spriteSourceSize": {
						"x": 1,
						"y": 2,
						"w": 12,
						"h": 33
					},
					"frame": {
						"x": 276,
						"y": 1,
						"w": 12,
						"h": 33
					}
				},
				{
					"filename": "walkcycle/walkcycle-19.png",
					"rotated": false,
					"trimmed": true,
					"sourceSize": {
						"w": 14,
						"h": 35
					},
					"spriteSourceSize": {
						"x": 1,
						"y": 2,
						"w": 12,
						"h": 33
					},
					"frame": {
						"x": 275,
						"y": 71,
						"w": 12,
						"h": 33
					}
				},
				{
					"filename": "walkcycle/walkcycle-20.png",
					"rotated": false,
					"trimmed": true,
					"sourceSize": {
						"w": 14,
						"h": 35
					},
					"spriteSourceSize": {
						"x": 1,
						"y": 2,
						"w": 12,
						"h": 33
					},
					"frame": {
						"x": 288,
						"y": 36,
						"w": 12,
						"h": 33
					}
				},
				{
					"filename": "walkcycle/walkcycle-22.png",
					"rotated": false,
					"trimmed": true,
					"sourceSize": {
						"w": 14,
						"h": 35
					},
					"spriteSourceSize": {
						"x": 1,
						"y": 2,
						"w": 12,
						"h": 33
					},
					"frame": {
						"x": 290,
						"y": 1,
						"w": 12,
						"h": 33
					}
				},
				{
					"filename": "walkcycle/walkcycle-23.png",
					"rotated": false,
					"trimmed": true,
					"sourceSize": {
						"w": 14,
						"h": 35
					},
					"spriteSourceSize": {
						"x": 2,
						"y": 2,
						"w": 11,
						"h": 33
					},
					"frame": {
						"x": 289,
						"y": 71,
						"w": 11,
						"h": 33
					}
				},
				{
					"filename": "walkcycle/walkcycle-18.png",
					"rotated": false,
					"trimmed": true,
					"sourceSize": {
						"w": 14,
						"h": 35
					},
					"spriteSourceSize": {
						"x": 1,
						"y": 2,
						"w": 12,
						"h": 32
					},
					"frame": {
						"x": 302,
						"y": 36,
						"w": 12,
						"h": 32
					}
				},
				{
					"filename": "walkcycle/walkcycle-21.png",
					"rotated": false,
					"trimmed": true,
					"sourceSize": {
						"w": 14,
						"h": 35
					},
					"spriteSourceSize": {
						"x": 1,
						"y": 2,
						"w": 12,
						"h": 32
					},
					"frame": {
						"x": 304,
						"y": 1,
						"w": 12,
						"h": 32
					}
				},
				{
					"filename": "walkcycle/walkcycle-24.png",
					"rotated": false,
					"trimmed": true,
					"sourceSize": {
						"w": 14,
						"h": 35
					},
					"spriteSourceSize": {
						"x": 0,
						"y": 5,
						"w": 14,
						"h": 30
					},
					"frame": {
						"x": 302,
						"y": 70,
						"w": 14,
						"h": 30
					}
				}
			]
		}
	],
	"meta": {
		"app": "https://www.codeandweb.com/texturepacker",
		"version": "3.0",
		"smartupdate": "$TexturePacker:SmartUpdate:3b9bc1fc1e12bc2d93cb4769862abc15:90d5ef75196b85a529f182cc5ed120dc:cbce6b53f0f49e0bf15173c25c41f876$"
	}
}
